missImputeTS/__init__.py
missImputeTS/continuousTimeForm.py
missImputeTS/missImputeTS.py
missImputeTS/missTS.py
missImputeTS/na_kalman.py
missImputeTS/utils.py
missImputeTS/data/EuStockMarkets.csv
missImputeTS-0.0.0.21.dist-info/METADATA
missImputeTS-0.0.0.21.dist-info/WHEEL
missImputeTS-0.0.0.21.dist-info/top_level.txt
missImputeTS-0.0.0.21.dist-info/RECORD
