Metadata-Version: 2.1
Name: missImputeTS
Version: 0.0.0.21
Summary: The function 'missImputeTS' in this package is used to impute timeseries missing values particularly in the case of mixed-type data.It uses a random forest trained on the observed values of a data matrix to predict the missing values. It can be used to impute continuous and/or categorical data including complex interactions and non-linear relations. It can be run in parallel to save computation time.
Home-page: https://github.com/sean-mcclure/datapeek_py
Author: chang je Cho
Author-email: qkdrk7777775@gmail.com
License: MIT
Keywords: imputation,interpolation,missforest,imputets,missImputeTS
Platform: UNKNOWN
Requires-Dist: rPy2
Requires-Dist: pandas
Requires-Dist: numpy
Requires-Dist: scipy
Requires-Dist: sklearn
